[{"question": "what is on the table #PAD# #PAD# #PAD# #PAD# #PAD# #PAD# #PAD# #PAD# #PAD# #PAD#", "actual_answer": "nothing", "predicted_answer": "vase", "image_id": 230094, "batch_index": 0}, {"question": "is the woman happy #PAD# #PAD# #PAD# #PAD# #PAD# #PAD# #PAD# #PAD# #PAD# #PAD# #PAD#", "actual_answer": "no", "predicted_answer": "no", "image_id": 230061, "batch_index": 1}, {"question": "what is the name of the orange flower #PAD# #PAD# #PAD# #PAD# #PAD# #PAD# #PAD#", "actual_answer": "daisy", "predicted_answer": "daisy", "image_id": 114139, "batch_index": 2}, {"question": "how many clock faces are there #PAD# #PAD# #PAD# #PAD# #PAD# #PAD# #PAD# #PAD# #PAD#", "actual_answer": "1", "predicted_answer": "1", "image_id": 394504, "batch_index": 3}, {"question": "are the flowers in water #PAD# #PAD# #PAD# #PAD# #PAD# #PAD# #PAD# #PAD# #PAD# #PAD#", "actual_answer": "yes", "predicted_answer": "yes", "image_id": 152048, "batch_index": 4}, {"question": "is this bench partly made of wood #PAD# #PAD# #PAD# #PAD# #PAD# #PAD# #PAD# #PAD#", "actual_answer": "yes", "predicted_answer": "yes", "image_id": 114274, "batch_index": 5}, {"question": "are these roses #PAD# #PAD# #PAD# #PAD# #PAD# #PAD# #PAD# #PAD# #PAD# #PAD# #PAD# #PAD#", "actual_answer": "yes", "predicted_answer": "no", "image_id": 282894, "batch_index": 6}, {"question": "are the sheep chasing the cat #PAD# #PAD# #PAD# #PAD# #PAD# #PAD# #PAD# #PAD# #PAD#", "actual_answer": "yes", "predicted_answer": "yes", "image_id": 378272, "batch_index": 7}, {"question": "how many flowers are there #PAD# #PAD# #PAD# #PAD# #PAD# #PAD# #PAD# #PAD# #PAD# #PAD#", "actual_answer": "2", "predicted_answer": "2", "image_id": 439366, "batch_index": 8}, {"question": "what color flowers do you see #PAD# #PAD# #PAD# #PAD# #PAD# #PAD# #PAD# #PAD# #PAD#", "actual_answer": "yellow", "predicted_answer": "yellow and blue", "image_id": 147301, "batch_index": 9}, {"question": "are there people in the background #PAD# #PAD# #PAD# #PAD# #PAD# #PAD# #PAD# #PAD# #PAD#", "actual_answer": "no", "predicted_answer": "no", "image_id": 459723, "batch_index": 10}, {"question": "what color flower is in the vase #PAD# #PAD# #PAD# #PAD# #PAD# #PAD# #PAD# #PAD#", "actual_answer": "red", "predicted_answer": "red", "image_id": 35351, "batch_index": 11}, {"question": "is this a restaurant or a home #PAD# #PAD# #PAD# #PAD# #PAD# #PAD# #PAD# #PAD#", "actual_answer": "restaurant", "predicted_answer": "restaurant", "image_id": 190052, "batch_index": 12}, {"question": "do this elephants tusks reach the ground #PAD# #PAD# #PAD# #PAD# #PAD# #PAD# #PAD# #PAD#", "actual_answer": "yes", "predicted_answer": "yes", "image_id": 306975, "batch_index": 13}, {"question": "is the flowers in a vase #PAD# #PAD# #PAD# #PAD# #PAD# #PAD# #PAD# #PAD# #PAD#", "actual_answer": "no", "predicted_answer": "no", "image_id": 455353, "batch_index": 14}]